instappium/__init__.py
instappium/appium_webdriver.py
instappium/instappium.py
instappium/common/__init__.py
instappium/common/database_engine.py
instappium/common/helper_functions.py
instappium/common/logger.py
instappium/common/quota_management.py
instappium/common/settings.py
instappium/common/stats.py
instappium/common/xpath.py
instappium/common/model/__init__.py
instappium/common/model/comment.py
instappium/common/model/post.py
instappium/common/model/user.py
instappium/engine/__init__.py
instappium/engine/fsm.py
instappium-0.0.2.dist-info/LICENSE
instappium-0.0.2.dist-info/METADATA
instappium-0.0.2.dist-info/WHEEL
instappium-0.0.2.dist-info/entry_points.txt
instappium-0.0.2.dist-info/top_level.txt
instappium-0.0.2.dist-info/RECORD
