Metadata-Version: 2.1
Name: instappium
Version: 0.0.2
Summary: Tool for automated Instagram interactions
Home-page: https://github.com/christophe-duc/InstAppium
Author: InstAppium Community at Github
Author-email: contact.instappium@gmail.com
Maintainer: InstAppium Community at Github
License: GPLv3
Download-URL: https://github.com/christophe-duc/InstAppium/archive/master.zip
Project-URL: How Tos, https://github.com/christophe-duc/InstAppium/tree/master/docs
Project-URL: Examples, https://github.com/christophe-duc/InstAppium/tree/master/quickstart_templates
Project-URL: Bug Reports, https://github.com/christophe-duc/InstAppium/issues
Project-URL: Source, https://github.com/christophe-duc/InstAppium/tree/master/instappium
Keywords: instappium python instagram automation          marketing promotion bot appium
Platform: win32
Platform: linux
Platform: linux2
Platform: darwin
Classifier: Development Status :: 4 - Beta
Classifier: Environment :: Console
Classifier: Environment :: Win32 (MS Windows)
Classifier: Environment :: MacOS X
Classifier: Environment :: Web Environment
Classifier: Intended Audience :: End Users/Desktop
Classifier: Intended Audience :: Developers
Classifier: Operating System :: Microsoft :: Windows
Classifier: Operating System :: POSIX :: Linux
Classifier: Operating System :: MacOS :: MacOS X
Classifier: Operating System :: Unix
Classifier: Programming Language :: Python
Classifier: Programming Language :: JavaScript
Classifier: Programming Language :: SQL
Classifier: Topic :: Utilities
Classifier: Topic :: Software Development :: Build Tools
Classifier: Programming Language :: Python :: 3
Classifier: Programming Language :: Python :: 3.4
Classifier: Programming Language :: Python :: 3.5
Classifier: Programming Language :: Python :: 3.6
Classifier: Programming Language :: Python :: 3.7
Classifier: Natural Language :: English
Requires-Python: >=3, !=3.0.*, !=3.1.*, !=3.2.*, !=3.3.*
Requires-Dist: transitions
Requires-Dist: selenium
Requires-Dist: Appium-Python-Client (>=0.50)
Requires-Dist: pure-python-adb (>=0.2.3.dev0)
Provides-Extra: test
Requires-Dist: tox ; extra == 'test'
Requires-Dist: virtualenv ; extra == 'test'
Requires-Dist: tox-venv ; extra == 'test'
